astrbot_canary/__init__.py
astrbot_canary/py.typed
astrbot_canary-0.1.0.dist-info/METADATA
astrbot_canary-0.1.0.dist-info/WHEEL
astrbot_canary-0.1.0.dist-info/licenses/LICENSE
astrbot_canary-0.1.0.dist-info/RECORD
