Metadata-Version: 2.4
Name: astrbot-canary
Version: 0.1.0
Summary: This is an unofficial support Astrbot.
Author-email: LIghtJUNction <LIghtJUNction.me@gmail.com>
License-File: LICENSE
Requires-Python: >=3.14
